hydrosurvey/__init__.py
hydrosurvey/cli.py
hydrosurvey/gui.py
hydrosurvey/interpolate.py
hydrosurvey/methods.py
hydrosurvey/sn.py
hydrosurvey/sdi/__init__.py
hydrosurvey/sdi/binary.py
hydrosurvey/sdi/corestick.py
hydrosurvey/sdi/pickfile.py
hydrosurvey/widgets/__init__.py
hydrosurvey/widgets/command_runner.py
hydrosurvey/widgets/eac.py
hydrosurvey/widgets/file_picker.py
hydrosurvey/widgets/interpolate_lake.py
hydrosurvey/widgets/sdi2csv.py
hydrosurvey-0.4.1.dist-info/METADATA
hydrosurvey-0.4.1.dist-info/WHEEL
hydrosurvey-0.4.1.dist-info/entry_points.txt
hydrosurvey-0.4.1.dist-info/licenses/LICENSE
hydrosurvey-0.4.1.dist-info/RECORD
