Metadata-Version: 2.4
Name: hydrosurvey
Version: 0.4.1
Summary: Tools for processing and analyzing hydroacoustic survey data from lakes and reservoirs
Project-URL: Homepage, https://github.com/dharhas/hydrosurvey
Project-URL: Repository, https://github.com/dharhas/hydrosurvey
Project-URL: Documentation, https://github.com/dharhas/hydrosurvey#readme
Project-URL: Issues, https://github.com/dharhas/hydrosurvey/issues
Project-URL: Changelog, https://github.com/dharhas/hydrosurvey/releases
Author-email: Dharhas Pothina <dharhas@gmail.com>
Maintainer-email: Dharhas Pothina <dharhas@gmail.com>
License: MIT
License-File: LICENSE
Keywords: GIS,bathymetry,hydroacoustic,interpolation,lakes,reservoirs,sediment,survey
Classifier: Development Status :: 4 - Beta
Classifier: Intended Audience :: Science/Research
Classifier: License :: OSI Approved :: MIT License
Classifier: Operating System :: OS Independent
Classifier: Programming Language :: Python :: 3
Classifier: Programming Language :: Python :: 3.10
Classifier: Programming Language :: Python :: 3.11
Classifier: Programming Language :: Python :: 3.12
Classifier: Topic :: Scientific/Engineering :: GIS
Classifier: Topic :: Scientific/Engineering :: Hydrology
Classifier: Topic :: Scientific/Engineering :: Visualization
Requires-Python: >=3.10
Requires-Dist: geopandas>=1.0.0
Requires-Dist: hydrofunctions>=0.2.0
Requires-Dist: matplotlib>=3.5.0
Requires-Dist: numpy>=1.21.0
Requires-Dist: pandas>=1.3.0
Requires-Dist: questionary>=1.10.0
Requires-Dist: scipy>=1.7.0
Requires-Dist: shapely>=1.8.0
Requires-Dist: tomli-w>=1.0.0
Requires-Dist: tqdm>=4.60.0
Requires-Dist: typer>=0.9.0
Provides-Extra: dev
Requires-Dist: build>=0.10.0; extra == 'dev'
Requires-Dist: hatch>=1.0.0; extra == 'dev'
Requires-Dist: mypy>=1.0.0; extra == 'dev'
Requires-Dist: pytest>=7.0.0; extra == 'dev'
Requires-Dist: ruff>=0.1.0; extra == 'dev'
Provides-Extra: gui
Requires-Dist: bokeh>=3.0.0; extra == 'gui'
Requires-Dist: geoviews>=1.9.0; extra == 'gui'
Requires-Dist: hvplot>=0.8.0; extra == 'gui'
Requires-Dist: jupyter-bokeh>=3.0.0; extra == 'gui'
Requires-Dist: panel>=1.0.0; extra == 'gui'
Provides-Extra: test
Requires-Dist: pytest-cov>=4.0.0; extra == 'test'
Requires-Dist: pytest>=7.0.0; extra == 'test'
